AE/tlb/verilog/memory.v
// memory.v

module memory (
    input clk,
    input rst,
    
    // Access Interface
    /*---------------------Accept request-----------------------------*/
    input mem_req_valid_i,          // Memory request valid
    output reg mem_req_ready_o,     // Memory request ready
    input [31:0] mem_addr_i,        // Memory address to be accessed
    /*----------------------Send response-----------------------------*/
    output reg mem_resp_valid_o,    // Memory response valid
    input mem_resp_ready_i,         // Memory response ready
    output reg [31:0] mem_data_o    // Memory read data
);

// Memory parameters
parameter MEM_SIZE = 1024;                    // Number of 32-bit words
parameter MEM_ADDR_WIDTH = $clog2(MEM_SIZE);  // Address width for word index

// State definitions
parameter IDLE        = 2'b00;
parameter READ_ACCESS = 2'b01;
parameter RESPOND     = 2'b10;

// Memory storage (4KB) - 32-bit word addressable
reg [31:0] mem [0:MEM_SIZE-1];

// Internal registers
reg [1:0] state, next_state;
reg [31:0] mem_addr_reg;

// Address translation: byte address to word index
// Assuming word-aligned accesses (ignore bottom 2 bits)
wire [MEM_ADDR_WIDTH-1:0] word_index = mem_addr_reg[MEM_ADDR_WIDTH+1:2];
wire addr_valid = (mem_addr_reg[31:2] < MEM_SIZE);

// ===================================================================
// Memory Access State Machine
// ===================================================================

// Sequential logic
always @(posedge clk) begin
    if (rst) begin
        state <= IDLE;
    end else begin
        state <= next_state;
    end
end

// Next state logic
always @(*) begin
    next_state = state;
    
    case (state)
        IDLE: begin
            if (mem_req_valid_i && mem_req_ready_o) begin
                next_state = READ_ACCESS;
            end
        end
        
        READ_ACCESS: begin
            next_state = RESPOND;
        end
        
        RESPOND: begin
            if (mem_resp_ready_i && mem_resp_valid_o) begin
                next_state = IDLE;
            end
        end
        
        default: begin
            next_state = IDLE;
        end
    endcase
end

// Output and control logic
always @(posedge clk) begin
    if (rst) begin
        mem_req_ready_o  <= 1'b1;
        mem_resp_valid_o <= 1'b0;
        mem_data_o       <= 32'h00000000;
        mem_addr_reg     <= 32'h00000000;
    end else begin

        case (state)
            IDLE: begin
                if (mem_req_valid_i && mem_req_ready_o) begin
                    // Accept request
                    mem_addr_reg    <= mem_addr_i;
                    mem_req_ready_o <= 1'b0;                  
                end else begin
                    mem_req_ready_o <= 1'b1;
                end
            end
            
            READ_ACCESS: begin
                // Data ready, prepare response
                if (addr_valid) begin
                    mem_data_o <= mem[word_index];
                end else begin
                    mem_data_o <= 32'h00000000; // Out-of-range access
                end
                mem_resp_valid_o <= 1'b1;
            end
            
            RESPOND: begin
                //mem_resp_valid_o <= 1'b1;
                if (mem_resp_ready_i && mem_resp_valid_o) begin
                    // Response accepted
                    mem_resp_valid_o <= 1'b0;
                    mem_req_ready_o  <= 1'b1;
                end
            end
            
            default: begin
                mem_req_ready_o  <= 1'b1;
                mem_resp_valid_o <= 1'b0;
            end
        endcase
    end
end

// Memory initialization with page table structure
integer i;
initial begin
    // Initialize all memory to zero
    for (i = 0; i < MEM_SIZE; i = i + 1) begin
        mem[i] = 32'h00000000;
    end
    
    // Root PT at 0x400 (word_index = 0x400>>2 = 256)
    mem[256 + 0] = 32'h00000801; // VPN[31:22]=0: L2 PT at 0x800, Valid
    mem[256 + 1] = 32'h12340000; // VPN[31:22]=1: Invalid entry (V == 0)
    mem[256 + 2] = 32'h00000000; // VPN[31:22]=2: Invalid entry
    
    // L2 PT at 0x800 (word index = 0x800>>2 = 512)  
    mem[512 + 0] = 32'h1000000F; // VPN[21:12]=0: PPN=0x10000, W|R|V
    mem[512 + 1] = 32'h1100000F; // VPN[21:12]=1: PPN=0x11000, W|R|V  
    mem[512 + 2] = 32'h12000003; // VPN[21:12]=2: PPN=0x12000, R|V (R-only)
    mem[512 + 3] = 32'h00000000; // VPN[21:12]=3: Invalid entry

    // To test the TLB replacement strategy (Insert in set 8)
    mem[512 + 24] = 32'h1234500F; // VPN[21:12]=0x18=24: PPN=0x12345, W|R|V
    mem[512 + 40] = 32'h2234500F; // VPN[21:12]=0x28=40: PPN=0x22345, W|R|V  
    mem[512 + 56] = 32'h3234500F; // VPN[21:12]=0x38=56: PPN=0x32345, W|R|V
    mem[512 + 72] = 32'h4234500F; // VPN[21:12]=0x48=72: PPN=0x42345, W|R|V
    mem[512 + 88] = 32'h5234500F; // VPN[21:12]=0x58=88: PPN=0x52345, W|R|V
    
    $display("Memory initialized with %d words", MEM_SIZE);
    $display("Page table structure (1024-word memory):");
    $display("  Root PT at 0x0400 (word index 256)");
    $display("  L2 PT at 0x0800 (word index 512)");
    $display("  Usable address range: 0x0000-0x%04X", (MEM_SIZE-1)*4);
end

// DEBUG: Memory monitoring for debugging
// always @(posedge clk) begin
//     if (mem_req_valid_i && mem_req_ready_o) begin
//         $display("[MEM] Request: addr=0x%08h, word_idx=%d", mem_addr_i, mem_addr_i[MEM_ADDR_WIDTH+1:2]);
//     end
//     if (mem_resp_valid_o && mem_resp_ready_i) begin
//         $display("[MEM] Response: data=0x%08h", mem_data_o);
//     end
// end

endmodule

AE/tlb/verilog/test_memory.v
// // 优化后的memory_read任务 - 正确的握手协议
// task memory_read(
//     input [31:0] addr,
//     output [31:0] data_result
// );
// begin
//     // 步骤1: 等待memory准备接受请求
//     @(posedge clk);
//     while (!mem_req_ready_o) @(posedge clk);
    
//     // 步骤2: 发送请求
//     mem_req_valid_i = 1'b1;
//     mem_addr_i = addr;
//     $display("  [READ] Sending request to addr=0x%08h", addr);
    
//     // 步骤3: 等待请求被接受
//     do @(posedge clk); while (!mem_req_ready_o || !mem_req_valid_i);
    
//     // 步骤4: 清除请求信号
//     mem_req_valid_i = 1'b0;
    
//     // 步骤5: 准备接收响应
//     mem_resp_ready_i = 1'b1;
    
//     // 步骤6: 等待响应
//     while (!mem_resp_valid_o) @(posedge clk);
    
//     // 步骤7: 获取数据
//     data_result = mem_data_o;
//     $display("  [READ] Received data=0x%08h", data_result);
    
//     // 步骤8: 等待一个时钟周期确保握手完成
//     @(posedge clk);
    
//     // 步骤9: 清除响应准备信号
//     mem_resp_ready_i = 1'b0;
//     @(posedge clk);
// end
// endtask

// test_memory.v
// Memory 模块单元测试 - 修复版本，确保所有地址都正确

//`timescale 1ns/1ps

module test_memory;

// Clock and reset
reg clk;
reg rst;

// Memory Interface
reg mem_req_valid_i;
wire mem_req_ready_o;
reg [31:0] mem_addr_i;

wire mem_resp_valid_o;
reg mem_resp_ready_i;
wire [31:0] mem_data_o;

// Test variables
integer test_passed;
integer test_failed;
reg [31:0] test_addr;
reg [31:0] expected_data;
reg [31:0] received_data;

// DUT instantiation
memory dut (
    .clk(clk),
    .rst(rst),
    .mem_req_valid_i(mem_req_valid_i),
    .mem_req_ready_o(mem_req_ready_o),
    .mem_addr_i(mem_addr_i),
    .mem_resp_valid_o(mem_resp_valid_o),
    .mem_resp_ready_i(mem_resp_ready_i),
    .mem_data_o(mem_data_o)
);

// Clock generation
always #5 clk = ~clk;

// Test tasks
task reset_dut;
begin
    rst = 1'b1;
    mem_req_valid_i = 1'b0;
    mem_resp_ready_i = 1'b0;
    mem_addr_i = 32'h00000000;
    @(posedge clk);
    @(posedge clk);
    rst = 1'b0;
    @(posedge clk);
end
endtask

// task memory_read(
//     input [31:0] addr,
//     output [31:0] data_result
// );
// begin
//     // Send memory request
//     //@(posedge clk);
//     wait(mem_req_ready_o);
//     mem_req_valid_i = 1'b1;
//     mem_addr_i = addr;
//     @(posedge clk);
//     @(posedge clk);
//     mem_req_valid_i = 1'b0;
    
//     // Wait for response
//     wait(mem_resp_valid_o);
//     data_result = mem_data_o;
//     mem_resp_ready_i = 1'b1;
//     @(posedge clk);
//     @(posedge clk);
//     mem_resp_ready_i = 1'b0;
//     @(posedge clk);
// end
// endtask

task memory_read(
    input  [31:0] addr,
    output [31:0] data_result
);
begin
    // 1. 等待 memory 接口准备好
    while (mem_req_ready_o !== 1'b1) begin
        @(mem_req_ready_o);  // 等待信号变化，再检查条件
    end

    // 2. 发起请求
    mem_req_valid_i = 1'b1;
    mem_addr_i      = addr;
    // @(posedge clk);
    // @(posedge clk);
    do @(posedge clk); while (mem_req_ready_o !== 1'b0);
    mem_req_valid_i = 1'b0;
    
    // 3. 等待响应
    while (mem_resp_valid_o !== 1'b1) begin
        @(mem_resp_valid_o); // 等待信号变化，再检查条件
    end
    data_result      = mem_data_o;
    mem_resp_ready_i = 1'b1;
    @(posedge clk);
    @(posedge clk);
    mem_resp_ready_i = 1'b0;
    @(posedge clk);
end
endtask


// task memory_read(
//     input [31:0] addr,
//     output [31:0] data_result
// );
// begin
//     @(posedge clk);
//     while (!mem_req_ready_o) @(posedge clk);

//     mem_req_valid_i = 1'b1;
//     mem_addr_i = addr;
//     @(posedge clk);
//     mem_req_valid_i = 1'b0;

//     while (!mem_resp_valid_o) @(posedge clk);
//     data_result = mem_data_o;
//     mem_resp_ready_i = 1'b1;
//     @(posedge clk);
//     mem_resp_ready_i = 1'b0;
// end
// endtask


task verify_result(
    input [31:0] got_data,
    input [31:0] exp_data,
    input [255:0] test_name
);
begin
    if (got_data !== exp_data) begin
        $display("ERROR [%s]: Data mismatch", test_name);
        $display("  Expected: 0x%08h", exp_data);
        $display("  Got:      0x%08h", got_data);
        test_failed = test_failed + 1;
    end else begin
        $display("PASS [%s]: data=0x%08h", test_name, got_data);
        test_passed = test_passed + 1;
    end
end
endtask

task verify_read(
    input [31:0] addr,
    input [31:0] exp_data,
    input [255:0] test_name
);
begin
    memory_read(addr, received_data);
    if (received_data !== exp_data) begin
        $display("ERROR [%s]: Data mismatch", test_name);
        $display("  Address:  0x%08h", addr);
        $display("  Expected: 0x%08h", exp_data);
        $display("  Got:      0x%08h", received_data);
        test_failed = test_failed + 1;
    end else begin
        $display("PASS [%s]: addr=0x%08h, data=0x%08h", test_name, addr, received_data);
        test_passed = test_passed + 1;
    end
end
endtask

// Main test sequence
integer i;
reg [31:0] rapid_addresses [0:4];
reg [31:0] rapid_expected [0:4];
reg [31:0] test_addresses [0:9];
reg [31:0] expected_values [0:9];
initial begin
    $dumpfile("test_memory.vcd");
    $dumpvars(0, test_memory);
    // Initialize
    clk = 1'b0;
    test_passed = 0;
    test_failed = 0;
    
    $display("========================================");
    $display("Memory Unit Test Starting (Fixed Version)");
    $display("========================================");
    
    // Test 1: Reset functionality
    $display("\n=== Test 1: Reset Functionality ===");
    reset_dut();
    if (!mem_req_ready_o) begin
        $display("ERROR: Memory not ready after reset");
        test_failed = test_failed + 1;
    end else begin
        $display("PASS: Memory ready after reset");
        test_passed = test_passed + 1;
    end
    
    // Test 2: Read uninitialized memory (should return 0)
    $display("\n=== Test 2: Read Uninitialized Memory ===");
    verify_read(32'h00000000, 32'h00000000, "Start of memory");
    verify_read(32'h00000004, 32'h00000000, "Word 1");
    verify_read(32'h00000100, 32'h00000000, "Different location");
    
    // Test 3: Read initialized page table entries
    $display("\n=== Test 3: Read Page Table Entries ===");
    
    // Root page table at 0x400 (word index 256)
    verify_read(32'h00000400, 32'h00000801, "Root PT entry 0");
    verify_read(32'h00000404, 32'h12340007, "Root PT entry 1");
    verify_read(32'h00000408, 32'h00000000, "Root PT entry 2 (invalid)");
    
    // Level 2 page table at 0x800 (word index 512)
    verify_read(32'h00000800, 32'h1000000F, "L2 PT entry 0");
    verify_read(32'h00000804, 32'h1100000F, "L2 PT entry 1");
    verify_read(32'h00000808, 32'h12000007, "L2 PT entry 2");
    verify_read(32'h0000080C, 32'h00000000, "L2 PT entry 3 (invalid)");
    
    // Test 4: Word alignment verification
    $display("\n=== Test 4: Word Alignment Test ===");
    verify_read(32'h00000400, 32'h00000801, "Word aligned 0x400");
    verify_read(32'h00000404, 32'h12340007, "Word aligned 0x404");
    verify_read(32'h00000408, 32'h00000000, "Word aligned 0x408");
    verify_read(32'h0000040C, 32'h00000000, "Word aligned 0x40C");
    
    // Test 5: Address boundary tests
    $display("\n=== Test 5: Address Boundary Tests ===");
    verify_read(32'h00000000, 32'h00000000, "Start of memory");
    verify_read(32'h00000FFC, 32'h00000000, "End of range (word 1023)");
    
    // Test 6: Out of range access
    $display("\n=== Test 6: Out of Range Access ===");
    verify_read(32'h00001000, 32'h00000000, "Just out of range");
    verify_read(32'h00010000, 32'h00000000, "Far out of range");
    
    // Test 7: Page table structure verification
    $display("\n=== Test 7: Page Table Structure Scan ===");
    $display("Root page table area (0x400-0x410):");
    for (test_addr = 32'h400; test_addr <= 32'h410; test_addr = test_addr + 4) begin
        memory_read(test_addr, received_data);
        $display("  0x%08h -> 0x%08h", test_addr, received_data);
    end
    
    $display("Level 2 page table area (0x800-0x810):");
    for (test_addr = 32'h800; test_addr <= 32'h810; test_addr = test_addr + 4) begin
        memory_read(test_addr, received_data);
        $display("  0x%08h -> 0x%08h", test_addr, received_data);
    end
    
    // Test 8: Back-to-back requests
    $display("\n=== Test 8: Back-to-Back Requests ===");
    verify_read(32'h00000400, 32'h00000801, "Back-to-back 1");
    verify_read(32'h00000800, 32'h1000000F, "Back-to-back 2");
    verify_read(32'h00000404, 32'h12340007, "Back-to-back 3");
    
    // Test 9: Response delay handling
    $display("\n=== Test 9: Response Delay Handling ===");
    fork
        begin
            memory_read(32'h00000400, received_data);
            verify_result(received_data, 32'h00000801, "Delayed response");
        end
        begin
            // Add some delay before accepting response
            wait(mem_resp_valid_o);
            repeat(3) @(posedge clk);
        end
    join
    
    //Test 10: Rapid requests
    $display("\n=== Test 10: Rapid Sequential Requests ===");
    
    rapid_addresses[0] = 32'h00000000; rapid_expected[0] = 32'h00000000;
    rapid_addresses[1] = 32'h00000400; rapid_expected[1] = 32'h00000801;
    rapid_addresses[2] = 32'h00000404; rapid_expected[2] = 32'h12340007;
    rapid_addresses[3] = 32'h00000800; rapid_expected[3] = 32'h1000000F;
    rapid_addresses[4] = 32'h00000804; rapid_expected[4] = 32'h1100000F;
    
    for (i = 0; i < 5; i = i + 1) begin
        memory_read(rapid_addresses[i], received_data);
        if (received_data !== rapid_expected[i]) begin
            $display("ERROR: Rapid test %d failed. addr=0x%08h, exp=0x%08h, got=0x%08h", 
                     i, rapid_addresses[i], rapid_expected[i], received_data);
            test_failed = test_failed + 1;
        end else begin
            $display("PASS: Rapid test %d: addr=0x%08h -> 0x%08h", 
                     i, rapid_addresses[i], received_data);
            test_passed = test_passed + 1;
        end
    end
    
    // Test 11: State machine robustness
    $display("\n=== Test 11: State Machine Robustness ===");
    
    // Send request but delay response acceptance
    @(posedge clk);
    mem_req_valid_i = 1'b1;
    mem_addr_i = 32'h00000400;
    @(posedge clk);
    mem_req_valid_i = 1'b0;
    
    // Wait for response but don't accept immediately
    wait(mem_resp_valid_o);
    repeat(5) @(posedge clk); // Wait several cycles
    
    // Now accept the response
    if (mem_data_o == 32'h00000801) begin
        $display("PASS: State machine handled delayed acceptance correctly");
        test_passed = test_passed + 1;
    end else begin
        $display("ERROR: State machine failed delayed acceptance test");
        test_failed = test_failed + 1;
    end
    
    mem_resp_ready_i = 1'b1;
    @(posedge clk);
    mem_resp_ready_i = 1'b0;
    @(posedge clk);
    
    // Final comprehensive test
    $display("\n=== Test 12: Comprehensive Address Test ===");
    
    test_addresses[0] = 32'h00000000; expected_values[0] = 32'h00000000;
    test_addresses[1] = 32'h00000400; expected_values[1] = 32'h00000801;
    test_addresses[2] = 32'h00000404; expected_values[2] = 32'h12340007;
    test_addresses[3] = 32'h00000408; expected_values[3] = 32'h00000000;
    test_addresses[4] = 32'h00000800; expected_values[4] = 32'h1000000F;
    test_addresses[5] = 32'h00000804; expected_values[5] = 32'h1100000F;
    test_addresses[6] = 32'h00000808; expected_values[6] = 32'h12000007;
    test_addresses[7] = 32'h0000080C; expected_values[7] = 32'h00000000;
    test_addresses[8] = 32'h00000FFC; expected_values[8] = 32'h00000000;
    test_addresses[9] = 32'h00001000; expected_values[9] = 32'h00000000;
    
    for (i = 0; i < 10; i = i + 1) begin
        memory_read(test_addresses[i], received_data);
        if (received_data !== expected_values[i]) begin
            $display("ERROR: Comprehensive test %d failed", i);
            $display("  addr=0x%08h, exp=0x%08h, got=0x%08h", 
                     test_addresses[i], expected_values[i], received_data);
            test_failed = test_failed + 1;
        end else begin
            $display("PASS: Comprehensive test %d", i);
            test_passed = test_passed + 1;
        end
    end
    
    // Final report
    #100;
    $display("\n========================================");
    $display("Memory Test Summary:");
    $display("  Tests Passed: %d", test_passed);
    $display("  Tests Failed: %d", test_failed);
    
    if (test_failed == 0) begin
        $display("  ALL TESTS PASSED!");
    end else begin
        $display("  SOME TESTS FAILED!");
    end
    $display("========================================");
    
    $finish;
end

// Timeout watchdog
initial begin
    #50000;
    $display("ERROR: Memory test timeout!");
    $finish;
end

// 状态监控
always @(posedge clk) begin
    $display("Time: %0t, State: %s, req_valid=%b, req_ready=%b, resp_valid=%b, resp_ready=%b", 
             $time,
             (dut.state == 2'b00) ? "IDLE" :
             (dut.state == 2'b01) ? "READ_ACCESS" :
             (dut.state == 2'b10) ? "RESPOND" : "UNKNOWN",
             mem_req_valid_i, mem_req_ready_o, mem_resp_valid_o, mem_resp_ready_i);
end

endmodule

AE/tlb/verilog/test_memory.vcd
$date
	Sun Sep  7 10:33:38 2025
$end
$version
	Icarus Verilog
$end
$timescale
	1s
$end
$scope module test_memory $end
$var wire 1 ! mem_resp_valid_o $end
$var wire 1 " mem_req_ready_o $end
$var wire 32 # mem_data_o [31:0] $end
$var reg 1 $ clk $end
$var reg 32 % mem_addr_i [31:0] $end
$var reg 1 & mem_req_valid_i $end
$var reg 1 ' mem_resp_ready_i $end
$var reg 32 ( received_data [31:0] $end
$var reg 1 ) rst $end
$var reg 32 * test_addr [31:0] $end
$var integer 32 + i [31:0] $end
$var integer 32 , test_failed [31:0] $end
$var integer 32 - test_passed [31:0] $end
$scope module dut $end
$var wire 1 $ clk $end
$var wire 32 . mem_addr_i [31:0] $end
$var wire 1 & mem_req_valid_i $end
$var wire 1 ' mem_resp_ready_i $end
$var wire 1 ) rst $end
$var wire 10 / word_index [9:0] $end
$var wire 1 0 addr_valid $end
$var reg 32 1 mem_addr_reg [31:0] $end
$var reg 32 2 mem_data_o [31:0] $end
$var reg 1 " mem_req_ready_o $end
$var reg 1 ! mem_resp_valid_o $end
$var reg 2 3 next_state [1:0] $end
$var reg 2 4 state [1:0] $end
$var integer 32 5 i [31:0] $end
$upscope $end
$scope task memory_read $end
$var reg 32 6 addr [31:0] $end
$var reg 32 7 data_result [31:0] $end
$upscope $end
$scope task reset_dut $end
$upscope $end
$scope task verify_read $end
$var reg 32 8 addr [31:0] $end
$var reg 32 9 exp_data [31:0] $end
$var reg 256 : test_name [255:0] $end
$upscope $end
$scope task verify_result $end
$var reg 32 ; exp_data [31:0] $end
$var reg 32 < got_data [31:0] $end
$var reg 256 = test_name [255:0] $end
$upscope $end
$upscope $end
$enddefinitions $end
#0
$dumpvars
bx =
bx <
bx ;
bx :
bx 9
bx 8
bx 7
bx 6
b10000000000 5
bx 4
b0 3
bx 2
bx 1
x0
bx /
b0 .
b0 -
b0 ,
bx +
bx *
1)
bx (
0'
0&
b0 %
0$
bx #
x"
x!
$end
#5
b0 /
10
b0 4
b0 1
b0 #
b0 2
0!
1"
1$
#10
0$
#15
0)
1$
#20
0$
#25
b1 3
1&
b0 6
b10100110111010001100001011100100111010000100000011011110110011000100000011011010110010101101101011011110111001001111001 :
b0 9
b0 8
b1 -
1$
#30
0$
#35
b10 3
0"
b1 4
1$
#40
0$
#45
1'
b0 7
b10 4
1!
b0 3
0&
1$
#50
0$
#55
1"
0!
b0 4
1$
#60
0$
#65
0'
1$
#70
0$
#75
b1 3
b100 %
b100 .
1&
b100 6
b10101110110111101110010011001000010000000110001 :
b100 8
b10 -
b0 (
1$
#80
0$
#85
b10 3
b1 /
b1 4
0"
b100 1
1$
#90
0$
#95
1'
1!
b10 4
b0 3
0&
1$
#100
0$
#105
b0 4
1"
0!
1$
#110
0$
#115
0'
1$
#120
0$
#125
b1 3
b100000000 %
b100000000 .
1&
b100000000 6
b10001000110100101100110011001100110010101110010011001010110111001110100001000000110110001101111011000110110000101110100011010010110111101101110 :
b100000000 8
b11 -
1$
#130
0$
#135
b1000000 /
b10 3
0"
b100000000 1
b1 4
1$
#140
0$
#145
1'
b10 4
1!
b0 3
0&
1$
#150
0$
#155
1"
0!
b0 4
1$
#160
0$
#165
0'
1$
#170
0$
#175
b1 3
b10000000000 %
b10000000000 .
1&
b10000000000 6
b10100100110111101101111011101000010000001010000010101000010000001100101011011100111010001110010011110010010000000110000 :
b100000000001 9
b10000000000 8
b100 -
1$
#180
0$
#185
b10 3
b100000000 /
b1 4
0"
b10000000000 1
1$
#190
0$
#195
1'
b100000000001 7
1!
b100000000001 #
b100000000001 2
b10 4
b0 3
0&
1$
#200
0$
#205
b0 4
1"
0!
1$
#210
0$
#215
0'
1$
#220
0$
#225
b1 3
b10000000100 %
b10000000100 .
1&
b10000000100 6
b10100100110111101101111011101000010000001010000010101000010000001100101011011100111010001110010011110010010000000110001 :
b10010001101000000000000000111 9
b10000000100 8
b101 -
b100000000001 (
1$
#230
0$
#235
b100000001 /
b10 3
0"
b10000000100 1
b1 4
1$
#240
0$
#245
1'
b10010001101000000000000000111 7
b10 4
1!
b10010001101000000000000000111 #
b10010001101000000000000000111 2
b0 3
0&
1$
#250
0$
#255
1"
0!
b0 4
1$
#260
0$
#265
0'
1$
#270
0$
#275
b1 3
b10000001000 %
b10000001000 .
1&
b10000001000 6
b1010010011011110110111101110100001000000101000001010100001000000110010101101110011101000111001001111001001000000011001000100000001010000110100101101110011101100110000101101100011010010110010000101001 :
b0 9
b10000001000 8
b110 -
b10010001101000000000000000111 (
1$
#280
0$
#285
b10 3
b100000010 /
b1 4
0"
b10000001000 1
1$
#290
0$
#295
1'
b0 7
1!
b0 #
b0 2
b10 4
b0 3
0&
1$
#300
0$
#305
b0 4
1"
0!
1$
#310
0$
#315
0'
1$
#320
0$
#325
b1 3
b100000000000 %
b100000000000 .
1&
b100000000000 6
b1001100001100100010000001010000010101000010000001100101011011100111010001110010011110010010000000110000 :
b10000000000000000000000001111 9
b100000000000 8
b111 -
b0 (
1$
#330
0$
#335
b1000000000 /
b10 3
0"
b100000000000 1
b1 4
1$
#340
0$
#345
1'
b10000000000000000000000001111 7
b10 4
1!
b10000000000000000000000001111 #
b10000000000000000000000001111 2
b0 3
0&
1$
#350
0$
#355
1"
0!
b0 4
1$
#360
0$
#365
0'
1$
#370
0$
#375
b1 3
b100000000100 %
b100000000100 .
1&
b100000000100 6
b1001100001100100010000001010000010101000010000001100101011011100111010001110010011110010010000000110001 :
b10001000000000000000000001111 9
b100000000100 8
b1000 -
b10000000000000000000000001111 (
1$
#380
0$
#385
b10 3
b1000000001 /
b1 4
0"
b100000000100 1
1$
#390
0$
#395
1'
b10001000000000000000000001111 7
1!
b10001000000000000000000001111 #
b10001000000000000000000001111 2
b10 4
b0 3
0&
1$
#400
0$
#405
b0 4
1"
0!
1$
#410
0$
#415
0'
1$
#420
0$
#425
b1 3
b100000001000 %
b100000001000 .
1&
b100000001000 6
b1001100001100100010000001010000010101000010000001100101011011100111010001110010011110010010000000110010 :
b10010000000000000000000000111 9
b100000001000 8
b1001 -
b10001000000000000000000001111 (
1$
#430
0$
#435
b1000000010 /
b10 3
0"
b100000001000 1
b1 4
1$
#440
0$
#445
1'
b10010000000000000000000000111 7
b10 4
1!
b10010000000000000000000000111 #
b10010000000000000000000000111 2
b0 3
0&
1$
#450
0$
#455
1"
0!
b0 4
1$
#460
0$
#465
0'
1$
#470
0$
#475
b1 3
b100000001100 %
b100000001100 .
1&
b100000001100 6
b100110000110010001000000101000001010100001000000110010101101110011101000111001001111001001000000011001100100000001010000110100101101110011101100110000101101100011010010110010000101001 :
b0 9
b100000001100 8
b1010 -
b10010000000000000000000000111 (
1$
#480
0$
#485
b10 3
b1000000011 /
b1 4
0"
b100000001100 1
1$
#490
0$
#495
1'
b0 7
1!
b0 #
b0 2
b10 4
b0 3
0&
1$
#500
0$
#505
b0 4
1"
0!
1$
#510
0$
#515
0'
1$
#520
0$
#525
b1 3
b10000000000 %
b10000000000 .
1&
b10000000000 6
b10101110110111101110010011001000010000001100001011011000110100101100111011011100110010101100100001000000011000001111000001101000011000000110000 :
b100000000001 9
b10000000000 8
b1011 -
b0 (
1$
#530
0$
#535
b100000000 /
b10 3
0"
b10000000000 1
b1 4
1$
#540
0$
#545
1'
b100000000001 7
b10 4
1!
b100000000001 #
b100000000001 2
b0 3
0&
1$
#550
0$
#555
1"
0!
b0 4
1$
#560
0$
#565
0'
1$
#570
0$
#575
b1 3
b10000000100 %
b10000000100 .
1&
b10000000100 6
b10101110110111101110010011001000010000001100001011011000110100101100111011011100110010101100100001000000011000001111000001101000011000000110100 :
b10010001101000000000000000111 9
b10000000100 8
b1100 -
b100000000001 (
1$
#580
0$
#585
b10 3
b100000001 /
b1 4
0"
b10000000100 1
1$
#590
0$
#595
1'
b10010001101000000000000000111 7
1!
b10010001101000000000000000111 #
b10010001101000000000000000111 2
b10 4
b0 3
0&
1$
#600
0$
#605
b0 4
1"
0!
1$
#610
0$
#615
0'
1$
#620
0$
#625
b1 3
b10000001000 %
b10000001000 .
1&
b10000001000 6
b10101110110111101110010011001000010000001100001011011000110100101100111011011100110010101100100001000000011000001111000001101000011000000111000 :
b0 9
b10000001000 8
b1101 -
b10010001101000000000000000111 (
1$
#630
0$
#635
b100000010 /
b10 3
0"
b10000001000 1
b1 4
1$
#640
0$
#645
1'
b0 7
b10 4
1!
b0 #
b0 2
b0 3
0&
1$
#650
0$
#655
1"
0!
b0 4
1$
#660
0$
#665
0'
1$
#670
0$
#675
b1 3
b10000001100 %
b10000001100 .
1&
b10000001100 6
b10101110110111101110010011001000010000001100001011011000110100101100111011011100110010101100100001000000011000001111000001101000011000001000011 :
b10000001100 8
b1110 -
b0 (
1$
#680
0$
#685
b10 3
b100000011 /
b1 4
0"
b10000001100 1
1$
#690
0$
#695
1'
1!
b10 4
b0 3
0&
1$
#700
0$
#705
b0 4
1"
0!
1$
#710
0$
#715
0'
1$
#720
0$
#725
b1 3
b0 %
b0 .
1&
b0 6
b10100110111010001100001011100100111010000100000011011110110011000100000011011010110010101101101011011110111001001111001 :
b0 8
b1111 -
1$
#730
0$
#735
b0 /
b10 3
0"
b0 1
b1 4
1$
#740
0$
#745
1'
b10 4
1!
b0 3
0&
1$
#750
0$
#755
1"
0!
b0 4
1$
#760
0$
#765
0'
1$
#770
0$
#775
b1 3
b111111111100 %
b111111111100 .
1&
b111111111100 6
b10001010110111001100100001000000110111101100110001000000111001001100001011011100110011101100101001000000010100001110111011011110111001001100100001000000011000100110000001100100011001100101001 :
b111111111100 8
b10000 -
1$
#780
0$
#785
b10 3
b1111111111 /
b1 4
0"
b111111111100 1
1$
#790
0$
#795
1'
1!
b10 4
b0 3
0&
1$
#800
0$
#805
b0 4
1"
0!
1$
#810
0$
#815
0'
1$
#820
0$
#825
b1 3
b1000000000000 %
b1000000000000 .
1&
b1000000000000 6
b100101001110101011100110111010000100000011011110111010101110100001000000110111101100110001000000111001001100001011011100110011101100101 :
b1000000000000 8
b10001 -
1$
#830
0$
#835
b0 /
00
b10 3
0"
b1000000000000 1
b1 4
1$
#840
0$
#845
1'
b10 4
1!
b0 3
0&
1$
#850
0$
#855
1"
0!
b0 4
1$
#860
0$
#865
0'
1$
#870
0$
#875
b1 3
b10000000000000000 %
b10000000000000000 .
1&
b10000000000000000 6
b1000110011000010111001000100000011011110111010101110100001000000110111101100110001000000111001001100001011011100110011101100101 :
b10000000000000000 8
b10010 -
1$
#880
0$
#885
b10 3
b1 4
0"
b10000000000000000 1
1$
#890
0$
#895
1'
1!
b10 4
b0 3
0&
1$
#900
0$
#905
b0 4
1"
0!
1$
#910
0$
#915
0'
1$
#920
0$
#925
b1 3
b10000000000 %
b10000000000 .
1&
b10000000000 6
b10000000000 *
b10011 -
1$
#930
0$
#935
b100000000 /
10
b10 3
0"
b10000000000 1
b1 4
1$
#940
0$
#945
1'
b100000000001 7
b10 4
1!
b100000000001 #
b100000000001 2
b0 3
0&
1$
#950
0$
#955
1"
0!
b0 4
1$
#960
0$
#965
0'
1$
#970
0$
#975
b1 3
b10000000100 %
b10000000100 .
1&
b10000000100 6
b10000000100 *
b100000000001 (
1$
#980
0$
#985
b10 3
b100000001 /
b1 4
0"
b10000000100 1
1$
#990
0$
#995
1'
b10010001101000000000000000111 7
1!
b10010001101000000000000000111 #
b10010001101000000000000000111 2
b10 4
b0 3
0&
1$
#1000
0$
#1005
b0 4
1"
0!
1$
#1010
0$
#1015
0'
1$
#1020
0$
#1025
b1 3
b10000001000 %
b10000001000 .
1&
b10000001000 6
b10000001000 *
b10010001101000000000000000111 (
1$
#1030
0$
#1035
b100000010 /
b10 3
0"
b10000001000 1
b1 4
1$
#1040
0$
#1045
1'
b0 7
b10 4
1!
b0 #
b0 2
b0 3
0&
1$
#1050
0$
#1055
1"
0!
b0 4
1$
#1060
0$
#1065
0'
1$
#1070
0$
#1075
b1 3
b10000001100 %
b10000001100 .
1&
b10000001100 6
b10000001100 *
b0 (
1$
#1080
0$
#1085
b10 3
b100000011 /
b1 4
0"
b10000001100 1
1$
#1090
0$
#1095
1'
1!
b10 4
b0 3
0&
1$
#1100
0$
#1105
b0 4
1"
0!
1$
#1110
0$
#1115
0'
1$
#1120
0$
#1125
b1 3
b10000010000 %
b10000010000 .
1&
b10000010000 6
b10000010000 *
1$
#1130
0$
#1135
b100000100 /
b10 3
0"
b10000010000 1
b1 4
1$
#1140
0$
#1145
1'
b10 4
1!
b0 3
0&
1$
#1150
0$
#1155
1"
0!
b0 4
1$
#1160
0$
#1165
0'
1$
#1170
0$
#1175
b1 3
b100000000000 %
b100000000000 .
1&
b100000000000 6
b100000000000 *
1$
#1180
0$
#1185
b10 3
b1000000000 /
b1 4
0"
b100000000000 1
1$
